kiss_ai_stack_server/__init__.py
kiss_ai_stack_server/events/__init__.py
kiss_ai_stack_server/events/event_handlers.py
kiss_ai_stack_server/events/on_auth.py
kiss_ai_stack_server/events/on_close.py
kiss_ai_stack_server/events/on_init.py
kiss_ai_stack_server/events/on_query.py
kiss_ai_stack_server/events/on_store.py
kiss_ai_stack_server/models/__init__.py
kiss_ai_stack_server/models/db/__init__.py
kiss_ai_stack_server/models/db/session.py
kiss_ai_stack_server/routers/__init__.py
kiss_ai_stack_server/routers/rest_router.py
kiss_ai_stack_server/routers/ws_router.py
kiss_ai_stack_server/services/__init__.py
kiss_ai_stack_server/services/kiss_ai_agent_service.py
kiss_ai_stack_server/services/session_service.py
kiss_ai_stack_server/services/token_service.py
kiss_ai_stack_server/utilities/__init__.py
kiss_ai_stack_server/utilities/server_event_utils.py
kiss_ai_stack_server/utilities/session_auth_middleware.py
kiss_ai_stack_server/utilities/temp_file_manager.py
kiss_ai_stack_server-0.1.0a17.dist-info/LICENSE
kiss_ai_stack_server-0.1.0a17.dist-info/METADATA
kiss_ai_stack_server-0.1.0a17.dist-info/WHEEL
kiss_ai_stack_server-0.1.0a17.dist-info/top_level.txt
kiss_ai_stack_server-0.1.0a17.dist-info/RECORD
