Metadata-Version: 2.1
Name: kiss-ai-stack-server
Version: 0.1.0a17
Summary: KISS AI Stack's Server stub - Simplify AI Agent Development
Author: KISS AI Stack, Lahiru Pathirage
License: MIT
Project-URL: Homepage, https://github.com/kiss-ai-stack
Project-URL: Repository, https://github.com/kiss-ai-stack
Project-URL: Documentation, https://github.com/kiss-ai-stack/kiss-ai-stack-core/main/README.md
Keywords: ai,agent,machine-learning,llm,document-processing
Classifier: Development Status :: 3 - Alpha
Classifier: Intended Audience :: Developers
Classifier: License :: OSI Approved :: MIT License
Classifier: Programming Language :: Python :: 3.12
Classifier: Topic :: Scientific/Engineering :: Artificial Intelligence
Requires-Python: >=3.12
License-File: LICENSE
Requires-Dist: fastapi~=0.115.5
Requires-Dist: uvicorn~=0.32.1
Requires-Dist: websockets~=14.1
Requires-Dist: jose~=1.0.0
Requires-Dist: bcrypt~=4.2.1
Requires-Dist: tortoise-orm~=0.22.2
Requires-Dist: PyJWT~=2.10.1
Requires-Dist: starlette~=0.41.3
Requires-Dist: kiss-ai-stack-types~=0.1.0a2
Requires-Dist: kiss_ai_stack_core~=0.1.0a10
